minedag/__init__.py
minedag/minedag.py
tests/__init__.py
tests/conftest.py
tests/test_layer_iteration.py
tests/test_mine_dag.py
minedag-1.3.dist-info/LICENSE
minedag-1.3.dist-info/METADATA
minedag-1.3.dist-info/WHEEL
minedag-1.3.dist-info/top_level.txt
minedag-1.3.dist-info/RECORD
