Metadata-Version: 2.1
Name: minedag
Version: 1.3
Summary: Mine realisation of DAG
Home-page: https://github.com/moff4/minedag
Author: Komissarov Andrey
Author-email: Komissar.off.andrey@gmail.com
Classifier: Programming Language :: Python :: 3.10
Classifier: Programming Language :: Python :: 3.11
Classifier: Programming Language :: Python :: 3.12
Classifier: Programming Language :: Python :: 3.13
Classifier: Operating System :: OS Independent
License-File: LICENSE
